keylogging_analysis/__init__.py
keylogging_analysis/classes.py
keylogging_analysis/help_functions.py
keylogging_analysis/data/lh_default.csv
keylogging_analysis/data/ll_default.csv
keylogging_analysis-0.0.1.dist-info/METADATA
keylogging_analysis-0.0.1.dist-info/WHEEL
keylogging_analysis-0.0.1.dist-info/licenses/LICENSE
keylogging_analysis-0.0.1.dist-info/RECORD
