Metadata-Version: 2.4
Name: keylogging-analysis
Version: 0.0.1
Summary: keylogging_analysis is a Python module aimed at processsing and analysing data from the Language Hero ("lh") and Language Lab ("ll") datasets. It is useful to researchers interested in L2 language fluency, chatbot-student interactions or keylogging data.
Project-URL: Homepage, https://github.com/kobe-th/keylogging_analysis
Project-URL: Issues, https://github.com/kobe-th/keylogging_analysis/issues
Author-email: Kobe Thonissen <kobe.thonissen@gmail.com>
Maintainer-email: Serge Bibauw <serge.bibauw@uclouvain.be>
License-Expression: MIT
License-File: LICENSE
Classifier: License :: OSI Approved :: BSD License
Classifier: Operating System :: OS Independent
Classifier: Programming Language :: Python :: 3
Requires-Python: >=3.9
Requires-Dist: numpy>=1.21
Requires-Dist: pandas>=1.3
Requires-Dist: polars>=0.17
